{
    "Welcome to Flowback": "Välkommen till Flowback",
    "Go to login page": "Logga in",
    "Login": "Logga in",
    "Register": "Registrera",
    "Flowback Groups": "Flowback grupper",
    "Email": "Email",
    "Password": "Lösenord",
    "Not Finished": "Igång",
    "Forgot password?": "Glömt lösenordet?",
    "Do you want Email Notifications?": "Vill du ha notifikationer via email?",
    "Create a Proposal": "Skapa förslag",
    "Or enter as Guest": "Eller se sidan som gäst",
    "Search users": "Sök användare",
    "Search groups": "Sök grupper",
    "Timepolls": "Tidspolls",
    "Time polls at": "Tidspoller vid",
    "Server Error": "Serverproblem",
    "Name": "Namn",
    "Retype Password": "Upprepa lösenord",
    "I accept the Terms & Conditions": "Jag accepterar Terms & Conditions",
    "Passwords need to match": "Lösenorden måste matcha",
    "Something went wrong": "Något gick fel",
    "Wrong username or password": "Fel användarnamn eller lösenord",
    "Username": "Användarnamn",
    "Account was created but was unable to sign in": "Kontot skapades men kunde inte logga in",
    "Leave no field empty": "Fyll i alla fält",
    "Do you accept terms and conditions?": "Accepterar du?",
    "Please choose a name, i.e. your real name or your nich name. This name will be shown to others to identify you": "Välj ett namn som kommer synas på forumet för andra",
    "Reset password by typing your account email below to receive verification code": "Återställ lösenordet genom att skriva ditt email nedan för att få verifikationskoden, stäng inte denna sida",
    "Mail": "Email",
    "Send": "Skicka",
    "Login/Register": "Inloggning/Registrering",
    "Feed": "Flow",
    "Warning": "Varning",
    "Any Poll Type": "Alla polltyper",
    "Any Poll Progress": "Alla pollstatus",
    "Search here": "Sök här",
    "Ranking": "Rankning",
    "For/Against": "För/Emot",
    "With Endtime": "Med Slutdatum",
    "Public?": "Publikt?",
    "Endtime": "Slutdatum",
    "Cardinal": "Kardinal",
    "In progress": "Oavslutad",
    "This polltype is not implemented yet": "Den här polltypen är ej implementerad ännu",
    "Finished": "Avslutad",
    "Creator": "Skapare",
    "Created": "Skapad",
    "Ends": "Avslutas",
    "Comments": "Kommentarer",
    "Chat": "Chatt",
    "Private Messages": "Privata meddelanden",
    "Group Chats": "Gruppchatter",
    "Dynamic": "Dynamisk",
    "Scheduled": "Schemalagd",
    "Home": "Hem",
    "Public": "Publikt",
    "Groups": "Grupper",
    "Group": "Grupp",
    "Schedule": "Schema",
    "User Profile": "Användarprofil",
    "Support": "Support",
    "Log Out": "Logga ut",
    "Support between 12:00 and 17:00 CET": "Support vardagar mellan 12:00 och 17:00",
    "Number: +46737482562": "Nummer: +46737482562",
    "Mail: flowbacktask@gmail.com": "Mail: flowbacktask@gmail.com",
    "Close": "Stäng",
    "You": "Du",
    "About User": "Om användaren",
    "No data added yet.": "Ingen beskrivning har angetts",
    "You are not connected to MetaMask": "Du är inte kopplad till MetaMask",
    "Connect to MetaMask": "Koppla till MetaMask",
    "Change Cover Image": "Byt cover-foto",
    "User Bio": "Användarbeskrivning",
    "null": "Ingen beskrivning har angetts",
    "Jan": "Jan",
    "Feb": "Feb",
    "Mar": "Mar",
    "Apr": "Apr",
    "May": "Maj",
    "Jun": "Jun",
    "Jul": "Jul",
    "Aug": "Aug",
    "Sep": "Sep",
    "Oct": "Okt",
    "Nov": "Nov",
    "Dec": "Dec",
    "Mon": "Mån",
    "Tue": "Tis",
    "Wed": "Ons",
    "Thu": "Tor",
    "Fri": "Fre",
    "Sat": "Lör",
    "Sun": "Sön",
    "Type of Member": "Typ av medlem",
    "members": "medlemmar",
    "Not member": "Inte medlem",
    "Member": "Medlem",
    "Delegate": "Delegat",
    "delegate": "delegat",
    "Admin": "Admin",
    "You can't leave this group": "Du kan inte lämna denna grupp",
    "Create Group": "Skapa en grupp",
    "Group name": "Gruppnamn",
    "Group description": "Gruppbeskrivning",
    "Profile Photo": "Gruppens profilbild",
    "Cover Photo": "Gruppens cover-bild",
    "Member request": "Medlemsansökan",
    "Direct Join": "Direktmedlem",
    "Needs Moderation": "Kräver godkännande",
    "Submit": "Acceptera",
    "End Date": "Slutdatum",
    "Select Tag": "Välj Tagg",

    "About": "Om",
    "Documents": "Dokument",
    "Members": "Medlemmar",
    "Send mail": "Skicka mail",
    "Successfully created role": "Roll skapad framgångsrikt",
    "Group statistics": "Gruppstatistik",
    "Statistics": "Statistik",
    "Create Poll": "Skapa poll",
    "Video Conference": "Videokonferens",
    "Description": "Beskrivning",
    "Created By": "Skapad av",
    "Add Document": "Lägg till dokument",
    "Create Co-Document": "Skapa co-dokument",
    "Join Requests": "Ansökningar",
    "Pending": "Väntande",
    "Not Member": "Inte medlem",
    "Select as Delegate": "Välj delegat",
    "Admin can't be a delegate": "Admin kan inte vara delegat",
    "Send Email": "Skicka Email",
    "Go to main folder": "Gå till huvudmappen",
    "My Kanban": "Min Kanban",
    "Create task": "Skapa ärende",
    "Add tag": "Lägg till tagg",
    "Direct": "Direkt",
    "Are you sure?": "Är du säker?",
    "Removing a tagg removes all polls with that tag!": "Att ta bort en tagg tar bort alla omröstningar med den taggen!",
    "Kick": "Ta bort",
    "Group Kanban": "Gruppkanban",
    "YES": "JA",
    "NO": "NEJ",
    "Timeline details": "Tidslinjens detaljer",
    "Can't vote after vote end date": "Kan inte rösta efter slutdatum",
    "Recommended ratios for images: 1:1 for profile, 4:1 for banner": "Rekommenderade förhållanden för bilder: 1:1 för profil, 4:1 för banner",
    "Voting Rights": "Rösträtt",
    "This group is only joinable by invitation": "Du kan endast gå med i denna grupp via inbjudan",
    "Successfully changed voting rights": "Rösträtt uppdaterad",
    "Become delegate": "Bli delegat",
    "Ask to join": "Be om att få gå med",
    "This will only work if you are an admin": "Detta fungerar endast om du är administratör",
    "Subject": "Ämne",
    "Content": "Innehåll",
    "Edit a Group": "Redigera Gruppen",
    "Edit profile": "Redigera Profil",
    "Advanced time settings": "Advancerade tidsinställningar",
    "Days between phases": "Dagar mellan faserna",
    "Already Loggin in, redirecting": "Redan inloggad, omdiregerar",
    "Update": "Uppdatera",
    "Create a poll": "Skapa en poll",
    "Poll name": "Pollnamn",
    "Add File": "Lägg till fil",
    "Add Details": "Beskrivning",
    "Create": "Skapa",
    "Edit": "Redigera",
    "a Poll": "en poll",
    "Private": "Privat inom grupp",
    "Voting Type": "Röstningstyp",
    "End Time": "Avslutningstid",
    "Quadratic": "Kvadratisk",
    "Upload Image, recomended ratio 1:1": "Ladda upp bild, rekommenderat förhållande 1:1",
    "Upload Cover Image, recomended ratio 4:1": "Ladda upp cover bild, rekomenderat förhålande 4:1",
    "Click here to get information about the different voting types": "Klicka här för information om röstningstyperna",
    "Ranking is the method of preferential voting known as the borda count. The top proposal in Added always gets the number of points as there are proposals (it does not depend on there being proposals below it), and the one below that gets that number minus one, the one below that gets that number minus two and so on. Each proposal that are in abstain each get zero points. This is added over all voters and is divided by the total number of votes to get the result.": "Rankning är metoden känd som borda-röstning. Alla förslag som inte rankas positivt får 0 poäng och den som rankas positivt högst får antalet poäng som det finns förslag, och den under får den poängen minus ett etc. Detta adderas över alla röstare och delas på antalet röstare för att räkna ut resultatet.",
    "For/Against is the method where each proposal that is voted for gets one point and each voted against gets minus one independently of order, all other proposals get zero points. The points are then added over all voters and is divided by the total number of votes to get the result.": "För/Emot är metoden där allt för får ett poäng och allt emot får minus ett poäng, sedan adderas rösterna över röstare och delas på antalet röstare för att få fram resultatet. Den metoden fungerar bäst när man endast ska se vad medlemmar är för och emot.",
    "Quadratic is the method where each member can rank by writing any number for all polls, which are ranked accordingly and get the percentage compared to the total that the member gives, the percentages are added up over all members and divided by the total to get the result. This means that not only are the proposals ranked by order of preference, but the degree by which one proposal is better than another is reflected. Totals will not exceed 10^6.": "Kvadratisk röstning är metoden där alla medlemmar kan ranka genom att skriva tal per förslag som rankas och talet delas på användares totala utgivna summa tal, vilket ger vilka andelar de röstar i, vilket adderas över röstare och delas på antalet röstare. Detta är viktningsröstning, vilket är bättre än rankning för proportionella val. Inga summor överstiger 10^6.",
    "Scheduled is the method where dates and times are voted on to decide meetings or events for the members of the group. Time polls are always Private and can only be seen by group members. One can only vote for a time or vote to drop the proposal, a default proposal for every time poll. This is carried out by the ranking method.": "Schemalagd röstning är metoden där datum och tider rankas via rankningsmetoden för att komma fram till ett enda förslag, de är alltid privata och det finns alltid ett standardalternativ att förkasta pollen.",
    "Cardinal currently has no description": "Kardinalröstning har ej en förklaring för tillfället",
    "An poll with an end date has a specified time when the poll finishes and results are displayed.": "En poll med slutdatum har ett specifierat datum där pollen avslutas och resultaten visas.",
    "A dynamic poll is always on and lacks an end date, results are always on display as they change dynamically.": "En dynamisk poll är alltid igång och resultatet räknas ut ständigt.",
    "Poll Status": "Pollstatus",
    "Meeting date": "Mötesdatum",
    "For questions about Metamask, contact the Metamask team.": "För frågor om Metamask, kontakta Metamask-teamet.",
    "Discussion": "Diskussion",
    "Voting": "Röstning",
    "Created at": "Skapad",
    "Accepted at": "Accepterad",
    "Sort Proposals": "Sortera förslag",
    "Save Votings": "Spara röstning",
    "Added": "Tillagt",
    "Successfully updated your vote": "Röstning uppdaterad",
    "Success": "Lyckades",
    "Abstain": "Avstå",
    "Proposal": "Förslag",
    "Title": "Titel",
    "Reply": "Svara",
    "Write a comment": "Skriv kommentar",
    "Replying to": "Besvara",
    "Download poll data and hash": "Ladda ner polldata och hash",
    "Reveal Results JSON object": "Visa resultat-JSON-objekt",
    "Reveal Result Hash": "Visa resultat-hash",
    "Edited": "Editerat",
    "Edit a Poll": "Editera en poll",
    "No winning proposal": "Inget vinnande förslag",
    "Approval": "Godkännande",
    "Created by": "Skapad av",
    "Join": "Gå med",
    "Leave": "Lämna",
    "Being a delegate means that members can select you as a delegate and copy your voting in every poll of the group, unless they alter the proposals in that particular poll.": "Att bli delegat innebär att alla medlemmar kan se vad du röstar och kan delegera till dig i varje poll i gruppen, om de inte ändrar något på den pollen själva.",
    "This decision is not reversible.": "Detta är oåterkallerligt.",
    "You have unsaved changes": "Du har osparade förändringar",
    "Average score": "Genomsnittlig poäng",
    "Nobody has voted yet": "Ingen har röstat ännu",
    "This prediction is finished and can no longer be voted on": "Denna prediktion är klar och kan inte längre bli röstad på",
    "Vote": "Rösta",
    "Unvote": "Ta bort röst",
    "All notifications": "Alla notifikationer",
    "Only timeline": "Endast tidslinje",
    "Cancel notifications": "Stäng av notifikationer",
    "No notifications": "Inga notifikationer",
    "Your current weight is": "Din nuvarande vikt är",
    "Task performed successfully!": "Lyckades!",
    "This prediction market is a point-based system dedicated to generating accurate predictions about future events by using the collective intelligence and wisdom. The number of steps better you guess than the average vote will change your weight positively in the voting and vice versa with negative (10 points plus or minus per step better or worse), that is only for the voting in the prediction market and not elsewhere. Your weight will be viewable by others.": "Denna förutsägelsemarknad är ett poängbaserat system dedikerat till att generera korrekta förutsägelser om framtida händelser genom att använda den kollektiva intelligensen och visdomen. Antalet steg bättre du gissar än den genomsnittliga rösten kommer att förändra din vikt positivt i omröstningen och vice versa med negativ (10 poäng plus eller minus per steg bättre eller sämre), det vill säga bara för röstningen på förutsägelsemarknaden och inte någon annanstans. Din vikt kommer att vara synlig för andra.",
    "Results": "Resultat",
    "What are prediction markets?": "Vad är prediktionsmarknaden?",
    "Prediction": "Prediktion",
    "Did happen": "Skedde",
    "Did not happen": "Skedde ej",
    "Click this button to create a co-document, share the link for others to edit it. Remember to save the link.": "Klicka på den här knappen för att skapa ett samdokument, dela länken så att andra kan redigera den. Kom ihåg att spara länken.",
    "Tools": "Verktyg",
    "Planned Time": "Planerad Tid",
    "Validate Votes": "Validera röster",
    "Decrypt vote": "Dekryptera röster",
    "Succesfully validated": "Lyckades validera",
    "private key": "privat nyckel",
    "Flowback Validator": "Flowback Validerare",
    "votes": "röster",
    "Something wen't wrong with decryption": "Någonting gick fel med dekrypteringen",
    "Go to Validator": "Gå till valideraren",
    "Polls for": "Poller på",
    "Proposal needs title": "Förslag behöver tittel",
    "Search for users": "Sök efter användare",
    "Character \"~\" is not allowed": "Karaktär \"~\" är inte tillåten",
    "Proposal with same title already exists": "Förslag med samma tittel finns redan",
    "Proposal with same date already exists": "Förslag med samma datum finns redan",
    "Start Chat": "Börja Chatta",
    "Backlog": "Logg",
    "Selected": "Valda",
    "Ongoing": "Pågående",
    "Permission Denied": "Ej tillåtet",
    "Current": "Pågende",
    "Review": "Granska",
    "Add Todo": "Lägg till Todo",
    "Edit Tags": "Redigera Taggar",
    "Edit Group": "Redigera Grupp",
    "Under Construction": "Under Utveckling",
    "This user has no bio": "Den här användaren har ingen bio",
    "Nothing this day": "Inget denna dag",
    "No delegates in group": "Inga delegater i gruppen",
    "Stop being delegate": "Sluta vara delegat",
    "Add as delegate": "Lägg till delegat",
    "Remove as delegate": "Ta bort delegat",
    "All": "Alla",
    "No delegates selected": "Inga delegater är valda",
    "Save changes": "Spara ändringar",
    "No polls currently here": "Inga röstningar uppladdade",
    "No polls currently here, join a group to see more": "Inga röstningar uppladdade, gå med i en grupp för att se mer.",
    "Edit tags for": "Redigera taggar för",
    "Delete poll": "Ta bort omröstning",
    "Delete": "Ta Bort",
    "Disable": "Inaktivera",
    "Successfully created proposal": "Lyckades skapa förslag",
    "Unable to log in with provided credentials.": "Kunde inte logga in med given information",
    "You are about to leave the group!": "Du är påväg att lämna gruppen!",
    "Successfully logged in": "Lyckades logga in",
    "User is not in group": "Användare är ej i gruppen",
    "To do": "Att göra",
    "Evaluation": "Under evaluering",
    "Done": "Avslutad",
    "Deleting Poll": "Ta bort omröstning",
    "Are you sure you want to delete this poll?": "Är du säker på att du vill ta bort omröstningen?",
    "Yes": "Ja",
    "No": "Nej",
    "Choose Image": "Välj bild",
    "Show earlier messages": "Visa nyare meddelanden",
    "New messages": "Nya meddelanden",
    "Show older messages": "Visa äldre meddelanden",
    "Time details": "Tidsdetaljer",
    "Timeline": "Fas",
    "Vote for": "Rösta för",
    "Upload Image": "Ladda upp bild",
    "Add Bio": "Lägg till bio",
    "Add Website": "Lägg till hemsida",
    "Banner Image": "Banner-bild",
    "(edited)": "(redigerad)",
    "Roles": "Roller",
    "Phone support is only between 15:30 and 17:30 CET": "Telefonsupport endast tillgänligt mellan 15:30 och 17:30",
    "You must accept terms of service to register": "Du måste acceptera användarvillkåren för att kunna registrera",
    "Flowback terms of service": "Flowbacks användarvillkor",
    "§1: the user agreeing to the terms of service means that they have acknowledged and accepted all of the terms fully and that they understand said terms.": "Att användaren godkänner användarvillkoren innebär att användaren har erkänt och accepterat alla villkoren till fullo och att användaren förstår dessa villkor.",
    "§2: the user may not post anything illegal going against Swedish law, otherwise their posts will be reported and removed from the site. The report-responsibility lies with every group owner, by creating a group this responsibility has been taken on by the creator user.": "Användaren får inte posta något olagligt som går emot svensk lag, annars kommer deras inlägg att rapporteras och tas bort från webbplatsen. Rapporteringsansvaret ligger på varje gruppägare, genom att skapa en grupp har detta ansvar övertagits av den skapande användaren.",
    "§3: the user guarantees that they are a real human being.": "§3: användaren garanterar att användaren är en riktig människa.",
    "§4: the terms of service is to be followed by all users.": "§4: användarvillkoren ska följas av alla användare.",
    "Note: your username will be public on the forum.": "Observera: ditt användarnamn kommer att vara offentligt på forumet.",
    "See delegate history": "Se delegat historik",
    "Unable to log in with provided credentials": "Det går inte att logga in med given information",
    "Create a Group": "Skapa grupp",
    "You are not a memeber of this group!": "Du är inte medlem av denna grupp!",
    "Upload Cover Image": "Ladda upp banner",
    "Manage Subscriptions": "Hantera Prenumerationer",
    "Chat is currently empty, maybe say hello?": "Chatten är för nuvarande tom, kanske dags att säga hej?",
    "No chat selected": "Ingen chatt vald",
    "Här är där du rangordnar dina förslag i ordning, där det högsta förslaget är det du helst vill att det röstas på": "Här är där du rangordnar dina förslag i ordning, där det högsta förslaget är det du helst vill att det röstas på",
    "My own": "Min egna",
    "Newest first": "Nyast först",
    "Oldest first": "Äldst först",
    "comments": "kommentarer",
    "Edit proposal": "Redigera förslag",
    "Enable buttons": "Tillåt knappar",
    "Successfully edited proposal": "Lyckades ändra förslag",
    "Mark all as read": "Markera alla som läst",
    "Proposal vote date": "Sista tid för förslag, röstning börjar",
    "Verification Code": "Verifikationskod",
    "Proposals": "Förslag",
    "Poll Start": "Startdatum",
    "Poll start": "Startdatum",
    "Delegate vote date": "Sista tid för delegater att rösta",
    "Delegate end date": "Sista tid för delegater att rösta",
    "Leave Group": "Lämna Grupp",
    "Leave group": "Lämna grupp",
    "Sync with Delegate": "Synkronisera med delegat",
    "Search": "Sök",
    "Server error": "Serverproblem",
    "Cancel": "Ångra",
    "at": "klockan",
    "Start date": "Startdatum",
    "End date": "Slutdatum",
    "Deleting group": "Tar bort grupp",
    "Are you sure you want to delete this group?": "Är du säker på att du vill ta bort gruppen?",
    "Delete Group": "Ta bort grupp"
}
